vcardgen/__init__.py
vcardgen/main.py
vcardgen/version.py
vcardgen-0.9.dist-info/DESCRIPTION.rst
vcardgen-0.9.dist-info/METADATA
vcardgen-0.9.dist-info/RECORD
vcardgen-0.9.dist-info/WHEEL
vcardgen-0.9.dist-info/entry_points.txt
vcardgen-0.9.dist-info/metadata.json
vcardgen-0.9.dist-info/top_level.txt
