Metadata-Version: 2.0
Name: vcardgen
Version: 0.9
Summary: 
Requires-Dist: PyZufall (>=0.13.1)
Requires-Dist: argparse
Requires-Dist: frogress (>=0.9.1)
Requires-Dist: future
Requires-Dist: kitchen
